snip/__init__.py
snip/__main__.py
snip/token/__init__.py
snip/token/__main__.py
snip/token/token.py
snip/token/storage/__init__.py
snip/token/storage/file_store.py
snip/token/storage/keyring_store.py
snip_lab-0.0.2.dist-info/METADATA
snip_lab-0.0.2.dist-info/WHEEL
snip_lab-0.0.2.dist-info/entry_points.txt
snip_lab-0.0.2.dist-info/licenses/LICENSE
snip_lab-0.0.2.dist-info/RECORD
