Metadata-Version: 2.3
Name: snip-lab
Version: 0.0.2
Summary: Placeholder for the snip package
Author-email: "Sebastian B. Mohr" <sebastianbernd.mohr@uni-goettingen.de>
License-File: LICENSE
Classifier: License :: OSI Approved :: MIT License
Classifier: Operating System :: OS Independent
Classifier: Programming Language :: Python :: 3
Requires-Python: >=3.9
Requires-Dist: keyring>=25.3.0
Requires-Dist: typer>=0.12.5
Provides-Extra: dev
Requires-Dist: pytest; extra == 'dev'
Requires-Dist: pytest-cov>=5.0.0; extra == 'dev'
